scmags/__init__.py
scmags/__main__.py
scmags/_api.py
scmags/_cli.py
scmags/_plot.py
scmags/datasets/__init__.py
scmags/datasets/_datasets.py
scmags/datasets/data/Baron_H1_Data.csv
scmags/datasets/data/Baron_H1_Gene_Ann.csv
scmags/datasets/data/Baron_H1_Labels.csv
scmags/datasets/data/Li_Data.csv
scmags/datasets/data/Li_Gene_Ann.csv
scmags/datasets/data/Li_Labels.csv
scmags/datasets/data/Pollen_Data.csv
scmags/datasets/data/Pollen_Gene_Ann.csv
scmags/datasets/data/Pollen_Labels.csv
scmags/tests/__init__.py
scmags/tests/test_scmags.py
scmags-1.7.dist-info/LICENSE
scmags-1.7.dist-info/METADATA
scmags-1.7.dist-info/WHEEL
scmags-1.7.dist-info/entry_points.txt
scmags-1.7.dist-info/top_level.txt
scmags-1.7.dist-info/RECORD
